{"lastupdated":"Tue, 03 Apr 2018 06:06:25 GMT","data":{"DZA":{"name":"Algeria","Community health workers (per 1,000 people)":{"2002":0.033,"2007":0.029}},"AUS":{"name":"Australia","Community health workers (per 1,000 people)":{"1996":0.039,"2001":0.197,"2006":0.049}},"BGD":{"name":"Bangladesh","Community health workers (per 1,000 people)":{"2004":0.328,"2005":0.147,"2011":0.393,"2012":0.476}},"BLZ":{"name":"Belize","Community health workers (per 1,000 people)":{"2009":0.503}},"BEN":{"name":"Benin","Community health workers (per 1,000 people)":{"2004":0.011}},"BTN":{"name":"Bhutan","Community health workers (per 1,000 people)":{"2007":0.684,"2012":0.862}},"BOL":{"name":"Bolivia","Community health workers (per 1,000 people)":{"2001":0.118}},"BWA":{"name":"Botswana","Community health workers (per 1,000 people)":{"1998":0.442,"1999":0.454,"2000":0.731,"2001":0.466,"2002":0.482,"2003":0.479,"2005":0.494,"2006":0.485,"2008":0.229,"2009":0.083}},"BFA":{"name":"Burkina Faso","Community health workers (per 1,000 people)":{"2004":0.099,"2006":0.091,"2010":0.126,"2012":0.127}},"BDI":{"name":"Burundi","Community health workers (per 1,000 people)":{"2004":0.086}},"CPV":{"name":"Cabo Verde","Community health workers (per 1,000 people)":{"2004":0.139}},"KHM":{"name":"Cambodia","Community health workers (per 1,000 people)":{"2004":0.125}},"CAF":{"name":"Central African Republic","Community health workers (per 1,000 people)":{"2004":0.053,"2008":0.408,"2009":0.393}},"TCD":{"name":"Chad","Community health workers (per 1,000 people)":{"2004":0.028}},"CHL":{"name":"Chile","Community health workers (per 1,000 people)":{"1992":0.021}},"CHN":{"name":"China","Community health workers (per 1,000 people)":{"1990":1.061,"1995":1.078,"1996":1.057,"1997":1.051,"1998":1.052,"1999":1.043,"2000":1.033,"2001":0.084,"2003":0.668,"2004":0.676,"2005":0.698,"2006":0.725,"2007":0.702,"2008":0.703,"2009":0.83,"2010":0.81,"2011":0.831}},"COM":{"name":"Comoros","Community health workers (per 1,000 people)":{"2004":0.068}},"COG":{"name":"Congo, Rep.","Community health workers (per 1,000 people)":{"2004":0.036}},"DJI":{"name":"Djibouti","Community health workers (per 1,000 people)":{"2004":0.03}},"GNQ":{"name":"Equatorial Guinea","Community health workers (per 1,000 people)":{"2004":2.103}},"EST":{"name":"Estonia","Community health workers (per 1,000 people)":{"2000":0.031}},"ETH":{"name":"Ethiopia","Community health workers (per 1,000 people)":{"2003":0.258,"2004":0.211,"2007":0.218,"2008":0.296,"2009":0.363}},"GMB":{"name":"Gambia, The","Community health workers (per 1,000 people)":{"2003":0.717,"2007":0.752,"2008":0.725}},"GHA":{"name":"Ghana","Community health workers (per 1,000 people)":{"1998":0.488,"1999":0.556,"2000":0.556,"2001":0.556,"2002":0.556,"2003":0.563,"2008":0.195}},"GRD":{"name":"Grenada","Community health workers (per 1,000 people)":{"1998":0.395,"1999":0.444,"2000":0.443,"2001":0.442,"2002":0.441,"2003":0.44}},"GIN":{"name":"Guinea","Community health workers (per 1,000 people)":{"2004":0.01,"2005":0.018}},"GNB":{"name":"Guinea-Bissau","Community health workers (per 1,000 people)":{"2004":3.133}},"GUY":{"name":"Guyana","Community health workers (per 1,000 people)":{"2009":0.326,"2010":0.325}},"IRN":{"name":"Iran, Islamic Rep.","Community health workers (per 1,000 people)":{"2004":0.364}},"IRQ":{"name":"Iraq","Community health workers (per 1,000 people)":{"2004":0.0058}},"JAM":{"name":"Jamaica","Community health workers (per 1,000 people)":{"2008":0.268}},"JOR":{"name":"Jordan","Community health workers (per 1,000 people)":{"2004":0.193}},"LBR":{"name":"Liberia","Community health workers (per 1,000 people)":{"2004":0.045}},"MWI":{"name":"Malawi","Community health workers (per 1,000 people)":{"2008":0.723}},"MYS":{"name":"Malaysia","Community health workers (per 1,000 people)":{"2010":0.435}},"MDV":{"name":"Maldives","Community health workers (per 1,000 people)":{"1991":4.04,"1993":3.897,"1996":3.081,"2004":3.064,"2007":2.488,"2009":1.934,"2010":2.421}},"MLI":{"name":"Mali","Community health workers (per 1,000 people)":{"2007":0.08,"2009":0.008,"2010":0.007}},"MRT":{"name":"Mauritania","Community health workers (per 1,000 people)":{"2004":0.14,"2009":0.278,"2013":0.3}},"MUS":{"name":"Mauritius","Community health workers (per 1,000 people)":{"2004":0.194}},"FSM":{"name":"Micronesia, Fed. Sts.","Community health workers (per 1,000 people)":{"2008":0.297}},"MNG":{"name":"Mongolia","Community health workers (per 1,000 people)":{"2008":0.023,"2009":0.123,"2010":0.161}},"MOZ":{"name":"Mozambique","Community health workers (per 1,000 people)":{"2012":0.047,"2013":0.045}},"MMR":{"name":"Myanmar","Community health workers (per 1,000 people)":{"2004":0.999,"2005":0.077,"2006":0.08,"2007":0.082,"2008":0.082,"2009":0.193,"2010":0.193,"2011":0.194,"2012":0.195}},"NRU":{"name":"Nauru","Community health workers (per 1,000 people)":{"2008":1.393,"2009":0.299}},"NPL":{"name":"Nepal","Community health workers (per 1,000 people)":{"2004":0.643}},"NGA":{"name":"Nigeria","Community health workers (per 1,000 people)":{"2004":0.851,"2007":0.131,"2008":0.128}},"PAK":{"name":"Pakistan","Community health workers (per 1,000 people)":{"1992":0.033,"1993":0.034,"1994":0.034,"1995":0.034,"1996":0.035,"1997":0.036,"1998":0.038,"1999":0.039,"2000":0.039,"2001":0.04,"2008":0.061,"2009":0.064,"2010":0.068}},"PAN":{"name":"Panama","Community health workers (per 1,000 people)":{"2000":0.46}},"PNG":{"name":"Papua New Guinea","Community health workers (per 1,000 people)":{"2008":0.594}},"RWA":{"name":"Rwanda","Community health workers (per 1,000 people)":{"2004":1.359}},"STP":{"name":"Sao Tome and Principe","Community health workers (per 1,000 people)":{"2004":2.498}},"SLE":{"name":"Sierra Leone","Community health workers (per 1,000 people)":{"2004":0.115,"2008":0.024,"2010":0.023}},"SVK":{"name":"Slovak Republic","Community health workers (per 1,000 people)":{"2013":0.018}},"ZAF":{"name":"South Africa","Community health workers (per 1,000 people)":{"2004":0.192}},"KNA":{"name":"St. Kitts and Nevis","Community health workers (per 1,000 people)":{"1990":0.416,"1991":0.415,"1992":0.411,"1993":0.406,"1994":0.401,"1995":0.396,"1996":0.392,"1997":0.387,"1998":0.721,"1999":0.712,"2001":1.039}},"VCT":{"name":"St. Vincent and the Grenadines","Community health workers (per 1,000 people)":{"2000":0.417}},"SDN":{"name":"Sudan","Community health workers (per 1,000 people)":{"2004":0.186}},"SWZ":{"name":"Swaziland","Community health workers (per 1,000 people)":{"2004":4.293}},"THA":{"name":"Thailand","Community health workers (per 1,000 people)":{"2000":0.059}},"TLS":{"name":"Timor-Leste","Community health workers (per 1,000 people)":{"2004":1.721}},"TGO":{"name":"Togo","Community health workers (per 1,000 people)":{"2004":0.088}},"UGA":{"name":"Uganda","Community health workers (per 1,000 people)":{"2005":0.194}},"VUT":{"name":"Vanuatu","Community health workers (per 1,000 people)":{"2007":0.514,"2008":0.941}},"YEM":{"name":"Yemen, Rep.","Community health workers (per 1,000 people)":{"2004":0.302,"2010":0.001}},"ZMB":{"name":"Zambia","Community health workers (per 1,000 people)":{"2005":0.815,"2008":0.685}}}}